{"name":"e-zero","tagline":"Manage e01 files. Consolidate after a collection, duplicate, and verifiy. ","body":"e-zero\r\n======\r\nManage e01 files. Consolidate after a collection, duplicate, and verify. \r\n\r\nRequires python2.7, docopt, and ftk imager CLI.\r\n\r\nInstalling\r\n----------\r\n1) Download and install python2.7 https://www.python.org/download\r\n\r\n2) Download and install docopt https://github.com/docopt/docopt\r\n\r\n3) Download FTK Imager CLI http://www.accessdata.com/support/product-downloads\r\n\r\n4) Make FTK Imager CLI available in PATH. Either:\r\n\r\n\ta) Simple copy and paste all files for FTK Imager CLI in C:\\Windows\r\n\t\r\n\tb) Modify your PATH variable to include FTK Imager CLI.","google":"","note":"Don't delete this file! It's used internally to help with page regeneration."}